setup.cfg
setup.py
environment_utils/__init__.py
environment_utils/utils.py
environment_utils.egg-info/PKG-INFO
environment_utils.egg-info/SOURCES.txt
environment_utils.egg-info/dependency_links.txt
environment_utils.egg-info/requires.txt
environment_utils.egg-info/top_level.txt