Metadata-Version: 1.1
Name: environment-utils
Version: 1.2.0
Summary: Environment utils library
Home-page: https://github.com/borbamartin/environment-utils
Author: Martin Borba
Author-email: borbamartin@gmail.com
License: UNKNOWN
Download-URL: https://github.com/borbamartin/environment-utils/tarball/1.2.0
Keywords: environment,utils
Platform: UNKNOWN
